{
  "project_info": {
    "project_number": "952361057438",
    "project_id": "tryfirestore-kt",
    "storage_bucket": "tryfirestore-kt.appspot.com"
  },
  "client": [
    {
      "client_info": {
        "mobilesdk_app_id": "1:952361057438:android:90bfcbdc13cf28b28f8f8f",
        "android_client_info": {
          "package_name": "com.example.try_firestore"
        }
      },
      "oauth_client": [
        {
          "client_id": "952361057438-quiavi253nm7v75bkgr8lqpvjq5ar86h.apps.googleusercontent.com",
          "client_type": 1,
          "android_info": {
            "package_name": "com.example.try_firestore",
            "certificate_hash": "a7b9679efd187b8cac0f8e6711f2b9488735db7d"
          }
        },
        {
          "client_id": "952361057438-kj2ol4nag786tcgittdks70aq2kj7v9o.apps.googleusercontent.com",
          "client_type": 3
        }
      ],
      "api_key": [
        {
          "current_key": "AIzaSyAwhUMJmHYNFj2L8KwWTWA5Ornl8Em_Qqo"
        }
      ],
      "services": {
        "appinvite_service": {
          "other_platform_oauth_client": [
            {
              "client_id": "952361057438-kj2ol4nag786tcgittdks70aq2kj7v9o.apps.googleusercontent.com",
              "client_type": 3
            }
          ]
        }
      }
    }
  ],
  "configuration_version": "1"
}